top_github_scraper/__init__.py
top_github_scraper/scrape_repo.py
top_github_scraper/scrape_user.py
top_github_scraper/utils.py
top_github_scraper-0.1.1.6.dist-info/WHEEL
top_github_scraper-0.1.1.6.dist-info/METADATA
top_github_scraper-0.1.1.6.dist-info/RECORD
