Metadata-Version: 2.1
Name: top-github-scraper
Version: 0.1.1.6
Summary: Scrape top GitHub repositories and users based on keyword
Home-page: https://github.com/khuyentran1401/top-github-scraper
License: Apache-2.0
Keywords: GitHub,github-api,scraping,python
Author: khuyentran1401
Author-email: khuyentran1476@gmail.com
Requires-Python: >=3.7.1,<4.0
Classifier: License :: OSI Approved :: Apache Software License
Classifier: Programming Language :: Python :: 3
Classifier: Programming Language :: Python :: 3.8
Classifier: Programming Language :: Python :: 3.9
Requires-Dist: bs4 (>=0.0.1,<0.0.2)
Requires-Dist: ipython (>=7.21.0,<8.0.0)
Requires-Dist: pandas (>=1.2.2,<2.0.0)
Requires-Dist: python-dotenv (>=0.15.0,<0.16.0)
Requires-Dist: requests (>=2.25.1,<3.0.0)
Requires-Dist: rich (>=9.12.0,<10.0.0)
Requires-Dist: tqdm (>=4.58.0,<5.0.0)
Project-URL: Repository, https://github.com/khuyentran1401/top-github-scraper
